Metadata-Version: 2.4
Name: matrix-python-sdk
Version: 0.1.11
Summary: Python SDK for Matrix Hub — catalog search, entity detail, install, and remote management for agents, tools, and MCP servers.
Author-email: Ruslan Magana Vsevolodovna <contact@ruslanmv.com>
License-Expression: Apache-2.0
Project-URL: Homepage, https://github.com/agent-matrix/matrix-python-sdk
Project-URL: Issues, https://github.com/agent-matrix/matrix-python-sdk/issues
Project-URL: Repository, https://github.com/agent-matrix/matrix-python-sdk
Project-URL: Documentation, https://agent-matrix.github.io/matrix-python-sdk/
Classifier: Development Status :: 3 - Alpha
Classifier: Intended Audience :: Developers
Classifier: Programming Language :: Python :: 3
Classifier: Programming Language :: Python :: 3 :: Only
Classifier: Programming Language :: Python :: 3.11
Classifier: Programming Language :: Python :: 3.12
Classifier: Typing :: Typed
Requires-Python: <3.13,>=3.11
License-File: LICENSE
Requires-Dist: httpx<0.29,>=0.28
Requires-Dist: pydantic<3.0,>=2.0
Requires-Dist: python-dotenv<2.0,>=1.1
Requires-Dist: truststore>=0.8
Requires-Dist: tomli>=2.0.1; python_version < "3.11"
Provides-Extra: cli
Requires-Dist: typer<0.10,>=0.9; extra == "cli"
Requires-Dist: rich<14.0,>=13.0; extra == "cli"
Provides-Extra: dev
Requires-Dist: pytest<9.0,>=8.0; extra == "dev"
Requires-Dist: pytest-asyncio<2.0,>=1.0; extra == "dev"
Requires-Dist: ruff<0.13,>=0.12; extra == "dev"
Requires-Dist: black; extra == "dev"
Requires-Dist: mypy; extra == "dev"
Requires-Dist: build; extra == "dev"
Requires-Dist: twine; extra == "dev"
Requires-Dist: mkdocs; extra == "dev"
Requires-Dist: pre-commit<3.0,>=2.20; extra == "dev"
Dynamic: license-file
